pystray/__init__.py
pystray/_appindicator.py
pystray/_base.py
pystray/_darwin.py
pystray/_dummy.py
pystray/_gtk.py
pystray/_info.py
pystray/_win32.py
pystray/_xorg.py
pystray/_util/__init__.py
pystray/_util/gtk.py
pystray/_util/notify_dbus.py
pystray/_util/win32.py
pystray_freedesktop-0.19.6a1.dist-info/licenses/COPYING
pystray_freedesktop-0.19.6a1.dist-info/licenses/COPYING.LGPL
pystray_freedesktop-0.19.6a1.dist-info/METADATA
pystray_freedesktop-0.19.6a1.dist-info/WHEEL
pystray_freedesktop-0.19.6a1.dist-info/top_level.txt
pystray_freedesktop-0.19.6a1.dist-info/RECORD
