Metadata-Version: 2.4
Name: pystray-freedesktop
Version: 0.19.6a1
Summary: A library to create system tray icons with freedesktop support (temporary fork).
Author-email: Moses Palmér <moses.palmer@gmail.com>, Sebastian Silva <sebastian@fuentelibre.org>
Maintainer-email: Sebastian Silva <sebastian@fuentelibre.org>
License: LGPL-3.0-or-later
Project-URL: Homepage, https://gtk-llm-chat.fuentelibre.org/
Project-URL: Repository, https://github.com/fuentelibre/gtk-llm-chat
Project-URL: Bug Reports, https://github.com/fuentelibre/gtk-llm-chat/issues
Classifier: Development Status :: 5 - Production/Stable
Classifier: License :: OSI Approved :: GNU Lesser General Public License v3 or later (LGPLv3+)
Classifier: Operating System :: MacOS :: MacOS X
Classifier: Operating System :: Microsoft :: Windows :: Windows NT/2000
Classifier: Operating System :: POSIX
Classifier: Programming Language :: Python
Classifier: Programming Language :: Python :: 3
Requires-Python: >=3.6
License-File: COPYING
License-File: COPYING.LGPL
Requires-Dist: Pillow
Requires-Dist: six
Dynamic: license-file
